py_gnat/__init__.py
py_gnat/gnat.py
py_gnat/greedy_k_centers.py
py_gnat/nearest_neighbors.py
py_gnat-0.2.0.dist-info/LICENSE
py_gnat-0.2.0.dist-info/METADATA
py_gnat-0.2.0.dist-info/WHEEL
py_gnat-0.2.0.dist-info/top_level.txt
py_gnat-0.2.0.dist-info/RECORD
