Metadata-Version: 2.1
Name: py_gnat
Version: 0.2.0
Summary: Python implementation of Geometric Near-neighbor Access Tree (GNAT) data structure from OMPL to search nearest neighbors.
Home-page: https://github.com/ZhuoyunZhong/py_gnat
Author: Zhuoyun Zhong
Author-email: zzy905954450@gmail.com
Classifier: Programming Language :: Python :: 3
Classifier: License :: OSI Approved :: MIT License
Classifier: Operating System :: OS Independent
Requires-Python: >=3.6
License-File: LICENSE
